tensorboard_plugin_netron/__init__.py
tensorboard_plugin_netron/plugin.py
tensorboard_plugin_netron-0.2.2.dist-info/LICENSE
tensorboard_plugin_netron-0.2.2.dist-info/METADATA
tensorboard_plugin_netron-0.2.2.dist-info/WHEEL
tensorboard_plugin_netron-0.2.2.dist-info/entry_points.txt
tensorboard_plugin_netron-0.2.2.dist-info/top_level.txt
tensorboard_plugin_netron-0.2.2.dist-info/RECORD
