Metadata-Version: 2.1
Name: tensorboard-plugin-netron
Version: 0.2.2
Summary: Netron TensorBoard Plugin
Home-page: https://sr.ht/~dhruvin/tensorboard-plugin-netron
Author: Dhruvin Gandhi
Author-email: contact@dhruvin.dev
License: MIT
Platform: UNKNOWN
Classifier: Programming Language :: Python :: 3
Classifier: License :: OSI Approved :: MIT License
Classifier: Operating System :: OS Independent
License-File: LICENSE
Requires-Dist: netron
Requires-Dist: tensorboard
Requires-Dist: werkzeug
